covid_nlp/__init__.py
covid_nlp/constant.py
covid_nlp/covid_nlp.py
covid_nlp/data.csv
tests/__init__.py
tests/test_number.py
Covid_NLP-0.0.1.dist-info/LICENSE
Covid_NLP-0.0.1.dist-info/METADATA
Covid_NLP-0.0.1.dist-info/WHEEL
Covid_NLP-0.0.1.dist-info/top_level.txt
Covid_NLP-0.0.1.dist-info/RECORD
